aix/__init__.py
aix/cli.py
aix/py.typed
aix/core/__init__.py
aix/core/ai_engine.py
aix/core/connector.py
aix/core/context.py
aix/core/conversation.py
aix/core/evaluator.py
aix/core/evasion.py
aix/core/owasp.py
aix/core/reporter.py
aix/core/request_parser.py
aix/core/scanner.py
aix/core/turn_evaluator.py
aix/core/chain_engine/__init__.py
aix/core/chain_engine/context.py
aix/core/chain_engine/executor.py
aix/core/chain_engine/playbook.py
aix/core/reporting/__init__.py
aix/core/reporting/base.py
aix/core/reporting/chain.py
aix/core/reporting/visualizer.py
aix/db/__init__.py
aix/db/database.py
aix/modules/__init__.py
aix/modules/agent.py
aix/modules/chain.py
aix/modules/dos.py
aix/modules/exfil.py
aix/modules/extract.py
aix/modules/fingerprint.py
aix/modules/fuzz.py
aix/modules/inject.py
aix/modules/jailbreak.py
aix/modules/leak.py
aix/modules/memory.py
aix/modules/multiturn.py
aix/modules/rag.py
aix/modules/recon.py
aix/payloads/__init__.py
aix/payloads/agent.json
aix/payloads/discovery_paths.json
aix/payloads/dos.json
aix/payloads/exfil.json
aix/payloads/extract.json
aix/payloads/fingerprint_db.json
aix/payloads/fuzz.json
aix/payloads/fuzz_config.json
aix/payloads/inject.json
aix/payloads/jailbreak.json
aix/payloads/leak.json
aix/payloads/leak_config.json
aix/payloads/memory.json
aix/payloads/multiturn.json
aix/payloads/rag.json
aix/payloads/recon.json
aix/payloads/recon_config.json
aix/payloads/refusals.json
aix/playbooks/data_exfil.yaml
aix/playbooks/full_compromise.yaml
aix/playbooks/prompt_theft.yaml
aix/playbooks/quick_scan.yaml
aix/playbooks/rag_pwn.yaml
aix/playbooks/stealth_recon.yaml
aix/prompts/__init__.py
aix/prompts/context_gathering.txt
aix/prompts/evaluator.txt
aix/prompts/evaluator_contextual.txt
aix/prompts/payload_generation.txt
aix/utils/__init__.py
aix/utils/cli.py
aix_framework-1.0.1.dist-info/licenses/LICENSE
aix_framework-1.0.1.dist-info/METADATA
aix_framework-1.0.1.dist-info/WHEEL
aix_framework-1.0.1.dist-info/entry_points.txt
aix_framework-1.0.1.dist-info/top_level.txt
aix_framework-1.0.1.dist-info/RECORD
