Metadata-Version: 2.4
Name: aix-framework
Version: 1.0.1
Summary: AIX - AI eXploit Framework: Comprehensive security testing toolkit for AI/LLM systems
Author-email: Simone Licitra <r08t@proton.me>
Maintainer-email: Simone Licitra <r08t@proton.me>
License: MIT
Project-URL: Homepage, https://github.com/licitrasimone/aix-framework
Project-URL: Documentation, https://github.com/licitrasimone/aix-framework#readme
Project-URL: Repository, https://github.com/licitrasimone/aix-framework.git
Project-URL: Issues, https://github.com/licitrasimone/aix-framework/issues
Project-URL: Changelog, https://github.com/licitrasimone/aix-framework/blob/main/CHANGELOG.md
Keywords: ai,llm,security,pentesting,red-team,prompt-injection,jailbreak,ai-security,vulnerability-scanner,owasp
Classifier: Development Status :: 4 - Beta
Classifier: Environment :: Console
Classifier: Intended Audience :: Developers
Classifier: Intended Audience :: Information Technology
Classifier: Intended Audience :: Science/Research
Classifier: License :: OSI Approved :: MIT License
Classifier: Natural Language :: English
Classifier: Operating System :: OS Independent
Classifier: Programming Language :: Python :: 3
Classifier: Programming Language :: Python :: 3 :: Only
Classifier: Programming Language :: Python :: 3.10
Classifier: Programming Language :: Python :: 3.11
Classifier: Programming Language :: Python :: 3.12
Classifier: Topic :: Security
Classifier: Topic :: Scientific/Engineering :: Artificial Intelligence
Classifier: Typing :: Typed
Requires-Python: >=3.10
License-File: LICENSE
Requires-Dist: click>=8.0.0
Requires-Dist: rich>=13.0.0
Requires-Dist: httpx[http2]>=0.25.0
Requires-Dist: aiohttp>=3.9.0
Requires-Dist: pyyaml>=6.0.0
Provides-Extra: full
Requires-Dist: mitmproxy>=10.0.0; extra == "full"
Requires-Dist: websockets>=12.0; extra == "full"
Provides-Extra: dev
Requires-Dist: pytest>=7.0.0; extra == "dev"
Requires-Dist: pytest-asyncio>=0.21.0; extra == "dev"
Requires-Dist: pytest-cov>=4.0.0; extra == "dev"
Requires-Dist: black>=23.0.0; extra == "dev"
Requires-Dist: ruff>=0.1.0; extra == "dev"
Requires-Dist: mypy>=1.0.0; extra == "dev"
Requires-Dist: pre-commit>=3.0.0; extra == "dev"
Provides-Extra: docs
Requires-Dist: mkdocs>=1.5.0; extra == "docs"
Requires-Dist: mkdocs-material>=9.0.0; extra == "docs"
Dynamic: license-file
